Workbook
Name ASOFDATE: ANR!$F$6
Name Period: #REF!
Name TICKER: ANR!#REF!

Sheet CONFIG
B1: MFIP Bloomberg Export Template — Master
C3: <-- TICKER (change me)
C4: <-- CURRENCY
B6: Lab Workflow — Instructions
B7: 1. Open this template on a Bloomberg Terminal lab PC (Bloomberg Excel Add-in must be loaded).
B8: 2. Change the ticker in cell B3 to your desired security (e.g., "DNB NO Equity", "AAPL US Equity").
B9: 3. Optionally change the reporting currency in B4 (USD, NOK, EUR, ...).
B10: 4. Wait ~30 seconds for all BDP() and BDH() calls across the seven data sheets to refresh.
B11: 5. Verify no #N/A Requesting Data... cells remain (press F9 if needed).
B12: 6. Select all (Ctrl+A) on each data sheet, Copy, then Paste Special > Values to freeze the data.
B13: 7. Save As: <TICKER>_<YYYY-MM-DD>.xlsx (e.g., DNB_2026-05-08.xlsx).
B14: 8. Done — the static export is ready for the MFIP report.
B16: Quick Reference — Key Metrics Extracted
B17: Sheet | C17: Data Type | D17: Bloomberg Function | E17: Key Fields | F17: Frequency
B18: BETA | C18: Beta & R-squared | D18: BDP | E18: BETA_RAW_OVERRIDABLE, BETA_ADJ_OVERRIDABLE, COEF_DETER_R_SQUARED | F18: Point-in-time
B19: DVD | C19: Dividend history | D19: BDS | E19: DVD_HIST_ALL (Decl, Ex, Record, Pay, Amt, Type, Ccy) | F19: All history
B20: EE | C20: Earnings estimates | D20: BDP | E20: BEST_EPS, BEST_LTG_EEPS, BEST_SALES, BEST_EBITDA, BEST_ANALYST_RATING | F20: Forward consensus
B21: RV_Comps | C21: Relative valuation | D21: BDP | E21: BEST_CUR_EV_TO_EBITDA , BEST_PE_RATIO, EV/Sales, PX_TO_BOOK_RATIO | F21: Point-in-time
B22: ANR | C22: Analyst recommendations | D22: BDP | E22: TOT_BUY_REC, TOT_HOLD_REC, TOT_SELL_REC, BEST_TARGET_PRICE, TOT_ANALYST_REC | F22: Point-in-time
B23: HP_Monthly | C23: Price history | D23: BDH | E23: PX_LAST (Per=cm) | F23: 10Y monthly
B24: HP_Daily | C24: Price history | D24: BDH | E24: PX_LAST (Per=cd) | F24: 5Y daily
B26: Note: All formulas reference CONFIG!$B$3 (ticker) and CONFIG!$B$4 (currency). Never hardcode a ticker on any sheet. Bloomberg Excel Add-in is required for live data.

Sheet BETA
B1: BETA — Raw, Adjusted, and R-squared
B3: Ticker | C3: =CONFIG!$B$3 -> 0
B5: Metric | C5: Value | D5: Bloomberg Field
B6: Raw Beta (overridable, 2Y weekly vs local index) | C6: =_xll.BDP(CONFIG!$B$3,$D$6) -> #NAME? | D6: BETA_RAW_OVERRIDABLE
B7: Adjusted Beta (Bloomberg adjusted) | C7: =_xll.BDP(CONFIG!$B$3,$D$7) -> #NAME? | D7: BETA_ADJ_OVERRIDABLE
B8: R-squared | C8: {=_xll.BDP(CONFIG!$B$3,$D$8)} -> #NAME? | D8: COEF_DETER_R_SQUARED

Sheet DVD
B1: DVD — Dividend History
B3: Ticker | C3: =CONFIG!$B$3 -> 0 | E3: Bloomberg Field | G3: DVD_HIST_ALL
B4: BDS returns the full dividend history. The array spills from B6. Columns: Declared Date | Ex-Date | Record Date | Payable Date | Amount | Frequency | Type
B5: Declared Date | C5: Ex-Date | D5: Record Date | E5: Payable Date | F5: Amount | G5: Frequency | H5: Type
B6: {=_xll.BDS(CONFIG!$B$3,"DVD_HIST_ALL")} -> #NAME?

Sheet EE
B1: EE — Earnings Estimates (Forward Consensus)
B3: Ticker | C3: =CONFIG!$B$3 -> 0
B4: Currency | C4: =CONFIG!$B$4 -> 0
B6: Metric | C6: Value | D6: Bloomberg Field
B7: Forward EPS (next fiscal year, BEst) | C7: =_xll.BDP(CONFIG!$B$3,$D$7,"BEST_FPERIOD_OVERRIDE","1FY","EQY_FUND_CRNCY",CONFIG!$B$4) -> #NAME? | D7: BEST_EPS
B8: Long-Term Growth (LTG, %) | C8: =_xll.BDP(CONFIG!$B$3,$D$8)% -> #NAME? | D8: BEST_LTG_EEPS
B9: Revenue Estimate (next fiscal year, BEst) | C9: =_xll.BDP(CONFIG!$B$3,$D$9,"BEST_FPERIOD_OVERRIDE","1FY","EQY_FUND_CRNCY",CONFIG!$B$4) -> #NAME? | D9: BEST_SALES
B10: EBITDA Estimate (next fiscal year, BEst) | C10: =_xll.BDP(CONFIG!$B$3,$D$10,"BEST_FPERIOD_OVERRIDE","1FY","EQY_FUND_CRNCY",CONFIG!$B$4) -> #NAME? | D10: BEST_EBITDA
B11: Consensus Rating (1=Buy, 5=Sell) | C11: =_xll.BDP(CONFIG!$B$3,$D$11) -> #NAME? | D11: BEST_ANALYST_RATING

Sheet ANR
B5: (Change settings below)
B6: Ticker | C6: =CONFIG!$B$3 -> 0 | D6: As of Date: | E6: =TODAY() -> 46150 | H6: Lookback Period: | M6: 2Y
B8: Buys % | C8: {=_xll.BQL($C$6,"#BuyPct","#AsofDate",_xll.BQL.DATE($E$6),"#BuyPct=TOT_BUY_REC(Dates=#AsofDate) / TOT_ANALYST_REC(Dates=#AsofDate)","Fill=Prev")} -> #NAME? | D8: Total Buys | E8: {=_xll.BQL($C$6,"#Buy","#AsofDate",_xll.BQL.DATE($E$6),"#Buy=TOT_BUY_REC(Dates=#AsofDate)","Fill=Prev")} -> #NAME?
B9: Holds % | C9: {=_xll.BQL($C$6,"#HoldPct","#AsofDate",_xll.BQL.DATE($E$6),"#HoldPct=TOT_HOLD_REC(Dates=#AsofDate) / TOT_ANALYST_REC(Dates=#AsofDate)","Fill=Prev")} -> #NAME? | D9: Total Holds | E9: {=_xll.BQL($C$6,"#Hold","#AsofDate",_xll.BQL.DATE($E$6),"#Hold=TOT_HOLD_REC(Dates=#AsofDate)","Fill=Prev")} -> #NAME?
B10: Sells % | C10: {=_xll.BQL($C$6,"#SellPct","#AsofDate",_xll.BQL.DATE($E$6),"#SellPct=TOT_SELL_REC(Dates=#AsofDate) / TOT_ANALYST_REC(Dates=#AsofDate)","Fill=Prev")} -> #NAME? | D10: Total Sells | E10: {=_xll.BQL($C$6,"#Sell","#AsofDate",_xll.BQL.DATE($E$6),"#Sell=TOT_SELL_REC(Dates=#AsofDate)","Fill=Prev")} -> #NAME?
B11: Rating | C11: {=_xll.BQL($C$6, "EQY_REC_CONS(Dates=#AsofDate)","#AsofDate",_xll.BQL.DATE($E$6))} -> #NAME? | D11: Currency | E11: {=_xll.BQL($C$6,"PX_LAST().currency")} -> #NAME?
B12: Target Price | C12: {=_xll.BQL($C$6, "LAST(#12MTgtPrice)","#Period",_xlfn.SINGLE(_xll.BQL.DATE($E$6))&" -"&$M$6,"#Date",_xll.BQL.DATE($E$6),"#12MTgtPrice = DROPNA(BEST_TARGET_PRICE(Dates=Range(#Period,#Date)))")} -> #NAME? | D12: Last Price | E12: {=_xll.BQL($C$6,"PX_LAST(Dates=#AsofDate)","#AsofDate",_xll.BQL.DATE($E$6),"Fill=Prev","XlFill=0")} -> #NAME?
B13: Return Potential | C13: =IFERROR(($C$12-$E$12)/$E$12,"-") -> - | D13: LTM Return | E13: {=_xll.BQL($C$6,"TOTAL_RETURN(CALC_INTERVAL=RANGE(#AsofDate-12M,#AsofDate))","#AsofDate",_xll.BQL.DATE($E$6),"Fill=Prev","XlFill=0")} -> #NAME?
B15: {=_xll.BDS($C$6,"BEST_ANALYST_RECS_BULK","END_DATE_OVERRIDE",TEXT(YEAR($E$6)*10000+MONTH($E$6)*100+DAY($E$6),"00000000"),"Headers=Y","StartCol=1","EndCol=3")} -> #NAME? | E15: {=_xll.BDS($C$6,"BEST_ANALYST_RECS_BULK","END_DATE_OVERRIDE",TEXT(YEAR($E$6)*10000+MONTH($E$6)*100+DAY($E$6),"00000000"),"Headers=Y","StartCol=6","EndCol=6","Fill=B")} -> #NAME? | F15: {=_xll.BDS($C$6,"BEST_ANALYST_RECS_BULK","END_DATE_OVERRIDE",TEXT(YEAR($E$6)*10000+MONTH($E$6)*100+DAY($E$6),"00000000"),"Headers=Y","StartCol=8","EndCol=8")} -> #NAME?
H32: Dates | I32: Target Price | J32: Last Price | K32: Buy % | L32: Hold % | M32: Sell % | N32: Price Spread
H33: #NAME?

Sheet HP_Monthly
B1: HP_Monthly — Historical Prices (10-Year, Monthly)
B3: Ticker | C3: =CONFIG!$B$3 -> 0
B4: BDH returns a 2-column array (Date | PX_LAST) that spills from B6. 10-year monthly close, last day of month.
B5: Date | C5: PX_LAST
B6: {=_xll.BDH(CONFIG!$B$3,"PX_LAST",TODAY()-3653,TODAY(),"Per=cm","Days=A","Fill=P")} -> #NAME?

Sheet HP_Daily
B1: HP_Daily — Historical Prices (5-Year, Daily)
B3: Ticker | C3: =CONFIG!$B$3 -> 0
B4: BDH returns a 2-column array (Date | PX_LAST) that spills from B6. 5-year daily close, weekdays only.
B5: Date | C5: PX_LAST
B6: {=_xll.BDH(CONFIG!$B$3,"PX_LAST",TODAY()-1826,TODAY(),"Per=cd","Days=W","Fill=P")} -> #NAME?
